<?xml version="1.0" encoding="iso-8859-1"?>
<database-types>
	<database>
		<name>Axion</name>
		<driverClassName>org.axiondb.jdbc.AxionDriver</driverClassName>
		<url>jdbc:axiondb:&lt;database-name&gt;[:&lt;database-directory&gt;]</url>	
	</database>
	
	<database>
		<name>Derby</name>
		<driverClassName>org.apache.derby.jdbc.ClientDriver</driverClassName>
		<url>jdbc:derby://&lt;server_name&gt;:&lt;port&gt;/&lt;databaseName&gt;[;create=true]</url>		
	</database>
	
	<database>
		<name>Oracle (Thin driver )</name>
		<driverClassName>oracle.jdbc.driver.OracleDriver</driverClassName>
		<url>jdbc:oracle:thin:@&lt;server&gt;[:&lt;1521&gt;]:&lt;database_name&gt;</url>		
	</database>	
</database-types>
